atmos_validation/__init__.py
atmos_validation/__main__.py
atmos_validation/convert_ascii/__init__.py
atmos_validation/convert_ascii/attrs_to_meta.py
atmos_validation/convert_ascii/df_to_nc.py
atmos_validation/convert_ascii/main.py
atmos_validation/convert_ascii/measurement_metadata_to_schema.json
atmos_validation/convert_ascii/parsers.py
atmos_validation/convert_ascii/utils.py
atmos_validation/schemas/__init__.py
atmos_validation/schemas/classification_level.py
atmos_validation/schemas/data_usability_level.py
atmos_validation/schemas/data_usability_levels.py
atmos_validation/schemas/dim_constants.py
atmos_validation/schemas/installation_type.py
atmos_validation/schemas/installation_types.py
atmos_validation/schemas/instrument_type.py
atmos_validation/schemas/instrument_types.py
atmos_validation/schemas/metadata.py
atmos_validation/schemas/parameter_config.py
atmos_validation/schemas/parameter_configs.py
atmos_validation/schemas/qc_tests.py
atmos_validation/schemas/tests/__init__.py
atmos_validation/schemas/tests/test_classification_level.py
atmos_validation/schemas/tests/test_parameter_configs.py
atmos_validation/schemas/tests/test_unique_configs.py
atmos_validation/validate_ascii/__init__.py
atmos_validation/validate_ascii/date_helper.py
atmos_validation/validate_ascii/header_date.py
atmos_validation/validate_ascii/header_metadata.py
atmos_validation/validate_ascii/header_names.py
atmos_validation/validate_ascii/header_parameter_info.py
atmos_validation/validate_ascii/header_parameter_info_list.py
atmos_validation/validate_ascii/header_parser.py
atmos_validation/validate_ascii/header_position.py
atmos_validation/validate_ascii/main.py
atmos_validation/validate_ascii/result_file.py
atmos_validation/validate_ascii/row_parser.py
atmos_validation/validate_ascii/utils.py
atmos_validation/validate_ascii/validate_result.py
atmos_validation/validate_netcdf/__init__.py
atmos_validation/validate_netcdf/main.py
atmos_validation/validate_netcdf/utils.py
atmos_validation-2.0.4.dist-info/METADATA
atmos_validation-2.0.4.dist-info/WHEEL
atmos_validation-2.0.4.dist-info/licenses/LICENSE
atmos_validation-2.0.4.dist-info/RECORD
