Metadata-Version: 2.4
Name: atmos_validation
Version: 2.0.4
Summary: A python library containing automated data validation tools for the Atmos Data Service
Project-URL: Repository, https://github.com/equinor/atmos-validation
Project-URL: Documentation, https://github.com/equinor/atmos-validation/tree/main/docs
Project-URL: Bug Reports, https://github.com/equinor/atmos-validation/issues
Project-URL: Changelog, https://github.com/equinor/atmos-validation/blob/main/CHANGELOG.md
Author: Team Atmos (Equinor)
License-Expression: MIT
License-File: LICENSE
Requires-Python: <3.14,>=3.10
Requires-Dist: dask<2026,>=2025.7.0
Requires-Dist: h5netcdf<2,>=1.6.4
Requires-Dist: h5py<4,>=3.10.0
Requires-Dist: numpy<3,>=2.0.0
Requires-Dist: pydantic<3,>=2.8.2
Requires-Dist: requests<3,>=2.32.4
Requires-Dist: xarray<2026,>=2025.0.0
